site_requests/__init__.py
site_requests/example.py
site_requests-0.0.6.dist-info/METADATA
site_requests-0.0.6.dist-info/WHEEL
site_requests-0.0.6.dist-info/licenses/LICENSE
site_requests-0.0.6.dist-info/RECORD
