Metadata-Version: 2.1
Name: site_requests
Version: 0.0.6
Summary: A small site requests package
Project-URL: Homepage, https://github.com/your-name/site-requests
Project-URL: Bug Tracker, https://github.com/your-name/site-requests/issues
Author-email: your name <you_mail@example.com>
License: MIT License
License-File: LICENSE
Classifier: License :: OSI Approved :: MIT License
Classifier: Operating System :: OS Independent
Classifier: Programming Language :: Python :: 3
Requires-Python: >=3.7
Requires-Dist: bs4==0.0.1
Requires-Dist: requests>=2.28.2
